{"4CtxRh1+asskHz2jIEMmVA==":"01.jpg","FaTe6FB74XsQfvHzrKm4sw==":"005-2000x1500.jpg","ADxrLGIIWAu8RwZwqN/hCw==":"003m-96x72.jpg","sGeWSKC6Ire88YZnssGu4A==":"p1-400x290.jpg","zgJDmRhSKRayEP1ZUWUYRQ==":"screenshot-w202club.ru-2022.05.17-17_54-32-101x720.png","0gOWaJ9Y2UEfoOqSSwbWyg==":"p2-450x169.jpg","Nv6dTg9po+7x9bsmiYqjEw==":"s28-1-200x180.jpg","/1YcNOrXEzOxJmgzXo2KFQ==":"s28-2-200x184.jpg","nP6QZAOi7q2+s/Pn7IIduA==":"s28-1-200x180.jpeg","pmFjpDOfobohvw06ZcJUgg==":"s28-2-200x180.jpeg","lUurWUPXHSbiF3jq5mGHJg==":"s28-3-200x192.jpg","F7Pbuq59/q62ViYkHc5ARQ==":"005-1266x950.jpg","rh0NasHaggXoWUTu42S4cA==":"s30-1-200x188.jpg","wnorc4tp/jEbv0n8bHtxqg==":"s30-2-200x185.jpg","jhWRZpqHMvukohMHSExlFg==":"s31-1-200x186.jpg","3/pPVmLngQEeIvlwxkyvuQ==":"s34-200x181.jpg","1hyOUlQfNkPaoGO3+k2Ucw==":"s35-1-200x182.jpg","YATmoHjjae9SAeVYNDynMg==":"s35-2-200x185.jpg","LbadDHJaoSSK3x1QtfScgQ==":"s35-3-200x183.jpg","KeqvGPdyfm96BYIa8qbQOg==":"s36-1-200x182.jpg","0mch5Q/cCWFqYu3YYfviUA==":"s36-2-200x181.jpg"}